fastapi_websocket_pubsub_plus/__init__.py
fastapi_websocket_pubsub_plus/event_broadcaster.py
fastapi_websocket_pubsub_plus/event_notifier.py
fastapi_websocket_pubsub_plus/exceptions.py
fastapi_websocket_pubsub_plus/logger.py
fastapi_websocket_pubsub_plus/pub_sub_client.py
fastapi_websocket_pubsub_plus/pub_sub_server.py
fastapi_websocket_pubsub_plus/rpc_event_methods.py
fastapi_websocket_pubsub_plus/util.py
fastapi_websocket_pubsub_plus/websocket_rpc_event_notifier.py
fastapi_websocket_pubsub_plus-0.1.1.dist-info/LICENSE
fastapi_websocket_pubsub_plus-0.1.1.dist-info/METADATA
fastapi_websocket_pubsub_plus-0.1.1.dist-info/WHEEL
fastapi_websocket_pubsub_plus-0.1.1.dist-info/top_level.txt
fastapi_websocket_pubsub_plus-0.1.1.dist-info/RECORD
