Metadata-Version: 2.1
Name: fastapi_websocket_pubsub_plus
Version: 0.1.1
Summary: A fast and durable PubSub channel over Websockets (using fastapi-websockets-rpc).
Home-page: https://github.com/vishal-singh-baraiya/fastapi_websocket_pubsub_plus
Author: Vishal Singh Baraiya
Author-email: realvixhal@gmail.com
Classifier: Programming Language :: Python :: 3
Classifier: License :: OSI Approved :: MIT License
Classifier: Operating System :: OS Independent
Classifier: Topic :: Internet :: WWW/HTTP :: HTTP Servers
Classifier: Topic :: Internet :: WWW/HTTP :: WSGI
Requires-Python: >=3.8
License-File: LICENSE
Requires-Dist: fastapi-websocket-rpc<1,>=0.1.25
Requires-Dist: packaging>=20.4
Requires-Dist: permit-broadcaster[kafka,postgres,redis]<3,>=0.2.5
Requires-Dist: pydantic>=1.9.1
Requires-Dist: websockets>=10.3
